hyperlist.py
hyperlist-0.1.dist-info/entry_points.txt
hyperlist-0.1.dist-info/LICENSE
hyperlist-0.1.dist-info/WHEEL
hyperlist-0.1.dist-info/METADATA
hyperlist-0.1.dist-info/RECORD
