Metadata-Version: 2.1
Name: hyperlist
Version: 0.1
Summary: 对原生list的二次封装
Keywords: 
Author-email: jutooy <jutooy@qq.com>
Classifier: License :: OSI Approved :: Apache Software License
